pcpartscraper
