Metadata-Version: 2.1
Name: pcpartscraper
Version: 1.1.0
Summary: A powerful pcpartpicker.com WebScraper that extracts Data from Part URL's and search Queries.
Home-page: https://github.com/Jeet-Chugh/pcpartscraper
Author: Jeet Chugh
Author-email: sunjeetchugh@gmail.com
License: MIT
Keywords: pcpartpicker
Platform: UNKNOWN
Classifier: Development Status :: 5 - Production/Stable
Classifier: Intended Audience :: Education
Classifier: Operating System :: Microsoft :: Windows :: Windows 10
Classifier: License :: OSI Approved :: MIT License
Classifier: Programming Language :: Python :: 3
